hotjar_data_wrapper/__init__.py
hotjar_data_wrapper/hotjar_api.py
hotjar_data_wrapper-0.1.5.dist-info/LICENSE
hotjar_data_wrapper-0.1.5.dist-info/METADATA
hotjar_data_wrapper-0.1.5.dist-info/WHEEL
hotjar_data_wrapper-0.1.5.dist-info/top_level.txt
hotjar_data_wrapper-0.1.5.dist-info/RECORD
