Metadata-Version: 2.1
Name: hotjar-data-wrapper
Version: 0.1.5
Summary: a wrapper for using Hotjar APIs
Author-email: Tobias McVey <tobias.mcvey@nav.no>
License: MIT License
Project-URL: Homepage, https://github.com/navikt/hotjar-data-wrapper
Keywords: hotjar
Requires-Python: >=3.10
License-File: LICENSE
Requires-Dist: requests
Requires-Dist: tqdm
Provides-Extra: dev
Requires-Dist: ipykernel ; extra == 'dev'
Requires-Dist: python-dotenv ; extra == 'dev'
Requires-Dist: black ; extra == 'dev'
Requires-Dist: twine ; extra == 'dev'
Requires-Dist: keyring ; extra == 'dev'
Requires-Dist: pip-tools ; extra == 'dev'
